adb_shell/__init__.py
adb_shell/adb_device.py
adb_shell/adb_device_async.py
adb_shell/adb_message.py
adb_shell/constants.py
adb_shell/exceptions.py
adb_shell/hidden_helpers.py
adb_shell/auth/__init__.py
adb_shell/auth/keygen.py
adb_shell/auth/sign_cryptography.py
adb_shell/auth/sign_pycryptodome.py
adb_shell/auth/sign_pythonrsa.py
adb_shell/transport/__init__.py
adb_shell/transport/base_transport.py
adb_shell/transport/base_transport_async.py
adb_shell/transport/tcp_transport.py
adb_shell/transport/tcp_transport_async.py
adb_shell/transport/usb_transport.py
adb_shell-0.4.3.dist-info/LICENSE
adb_shell-0.4.3.dist-info/METADATA
adb_shell-0.4.3.dist-info/WHEEL
adb_shell-0.4.3.dist-info/top_level.txt
adb_shell-0.4.3.dist-info/RECORD
