Metadata-Version: 2.1
Name: adb-shell
Version: 0.4.3
Summary: A Python implementation of ADB with shell and FileSync functionality.
Home-page: https://github.com/JeffLIrion/adb_shell
Author: Jeff Irion
Author-email: jefflirion@users.noreply.github.com
License: UNKNOWN
Keywords: adb,android
Platform: UNKNOWN
Classifier: Operating System :: OS Independent
Classifier: License :: OSI Approved :: Apache Software License
Classifier: Programming Language :: Python :: 3
Classifier: Programming Language :: Python :: 2
Provides-Extra: usb
Provides-Extra: async
License-File: LICENSE
